pparse/__init__.py
pparse/__main__.py
pparse/iam.py
pparse/policy.py
pparse-0.2.0.dist-info/LICENSE.txt
pparse-0.2.0.dist-info/METADATA
pparse-0.2.0.dist-info/WHEEL
pparse-0.2.0.dist-info/entry_points.txt
pparse-0.2.0.dist-info/top_level.txt
pparse-0.2.0.dist-info/RECORD
