Metadata-Version: 2.1
Name: pparse
Version: 0.2.0
Summary: Utility to parse and filter Google Cloud IAM policy documents.
Home-page: https://github.com/zefdelgadillo/policy-parser
Author: Zef Delgadillo
Author-email: zef.delgadillo@gmail.com
License: 'MIT License'
Keywords: google-cloud,gcp,iam
Platform: UNKNOWN
Classifier: Development Status :: 3 - Alpha
Classifier: License :: OSI Approved :: MIT License
Requires-Python: >=3.8, <4
License-File: LICENSE.txt
Requires-Dist: pyyaml
Requires-Dist: click
Requires-Dist: tabulate
Requires-Dist: pytest
Requires-Dist: google-api-python-client
Requires-Dist: oauth2client
